cmsplugin_formed_form/__init__.py
cmsplugin_formed_form/admin.py
cmsplugin_formed_form/cms_plugins.py
cmsplugin_formed_form/models.py
cmsplugin_formed_form/urls.py
cmsplugin_formed_form/views.py
cmsplugin_formed_form/migrations/0001_initial.py
cmsplugin_formed_form/migrations/0002_form_overrides.py
cmsplugin_formed_form/migrations/0003_form_finish_title.py
cmsplugin_formed_form/migrations/0004_form_source.py
cmsplugin_formed_form/migrations/0005_form_confirmation_email_show_summary.py
cmsplugin_formed_form/migrations/__init__.py
cmsplugin_formed_form/templates/plugins/formed_form/finish.html
cmsplugin_formed_form/templates/plugins/formed_form/form.html
cmsplugin_formed_form/templates/plugins/formed_form/summary.html
django_formed_cmsplugin-0.9.5.dist-info/LICENSE
django_formed_cmsplugin-0.9.5.dist-info/METADATA
django_formed_cmsplugin-0.9.5.dist-info/WHEEL
django_formed_cmsplugin-0.9.5.dist-info/top_level.txt
django_formed_cmsplugin-0.9.5.dist-info/zip-safe
django_formed_cmsplugin-0.9.5.dist-info/RECORD
