Metadata-Version: 2.1
Name: django-formed-cmsplugin
Version: 0.9.5
Summary: A DjangoCMS plugin which allows you to add a form created with django-formed to your page.
Home-page: https://bitbucket.org/frontendr/django-formed-cmsplugin
Author: Johan Arensman
Author-email: johan@frontendr.com
License: MIT
Keywords: DjangoCMS formed plugin
Platform: OS Independent
Classifier: Development Status :: 4 - Beta
Classifier: Intended Audience :: Developers
Classifier: License :: OSI Approved :: MIT License
Classifier: Operating System :: OS Independent
Classifier: Topic :: Internet :: WWW/HTTP
Classifier: Programming Language :: Python
Classifier: Programming Language :: Python :: 2.7
Classifier: Programming Language :: Python :: 3.5
Classifier: Framework :: Django
Classifier: Framework :: Django :: 1.8
Classifier: Framework :: Django :: 1.9
Classifier: Framework :: Django :: 1.10
Classifier: Framework :: Django :: 1.11
Requires-Dist: Django (<1.11.999,>=1.8)
Requires-Dist: django-formed (>=0.9.10)
